tablur/__init__.py
tablur/core.py
tablur-1.3.3.dist-info/licenses/LICENSE
tablur-1.3.3.dist-info/METADATA
tablur-1.3.3.dist-info/WHEEL
tablur-1.3.3.dist-info/top_level.txt
tablur-1.3.3.dist-info/RECORD
