Metadata-Version: 2.4
Name: tablur
Version: 1.3.3
Summary: A simple library for creating formatted tables with box-drawing characters
Home-page: https://github.com/durocodes/tablur
Author: Duro
Author-email: Duro <davidwright13503@gmail.com>
License: MIT
Project-URL: Homepage, https://github.com/durocodes/tablur
Project-URL: Repository, https://github.com/durocodes/tablur
Project-URL: Issues, https://github.com/durocodes/tablur/issues
Keywords: table,formatting,ascii,box-drawing,terminal,callable
Classifier: Development Status :: 4 - Beta
Classifier: Intended Audience :: Developers
Classifier: Operating System :: OS Independent
Classifier: Programming Language :: Python :: 3
Classifier: Programming Language :: Python :: 3.10
Classifier: Programming Language :: Python :: 3.11
Classifier: Programming Language :: Python :: 3.12
Requires-Python: >=3.10
License-File: LICENSE
Dynamic: author
Dynamic: home-page
Dynamic: license-file
Dynamic: requires-python
